diff_check_cli/__init__.py
diff_check_cli/cli.py
diff_check_cli/diff.py
diff_check_cli-0.1.4.dist-info/METADATA
diff_check_cli-0.1.4.dist-info/WHEEL
diff_check_cli-0.1.4.dist-info/entry_points.txt
diff_check_cli-0.1.4.dist-info/top_level.txt
diff_check_cli-0.1.4.dist-info/RECORD
