Metadata-Version: 2.4
Name: diff-check-cli
Version: 0.1.4
Summary: CLI для сравнения файлов/директорий/git-объектов
Author: Daniil Astrouski
Author-email: shelovesuastra@gmail.com
Requires-Python: >=3.7
Requires-Dist: click
Requires-Dist: rich
Requires-Dist: prompt-toolkit
Dynamic: author
Dynamic: author-email
Dynamic: description
Dynamic: description-content-type
Dynamic: requires-dist
Dynamic: requires-python
Dynamic: summary
